pythontwist/__init__.py
pythontwist-0.0.1.dist-info/METADATA
pythontwist-0.0.1.dist-info/RECORD
pythontwist-0.0.1.dist-info/WHEEL
pythontwist-0.0.1.dist-info/top_level.txt
