Metadata-Version: 2.1
Name: pythontwist
Version: 0.0.1
Summary: A small example package based on anime_downloader
Home-page: https://github.com/phanirithvij/twist.moe/tree/pythontwist
Author: Phani Rithvij
Author-email: phanirithvij2000@gmail.com
License: UNKNOWN
Platform: UNKNOWN
Classifier: Programming Language :: Python :: 3
Classifier: Operating System :: POSIX :: Linux
